<?xml version="1.0" encoding="UTF-8" ?>
<!DOCTYPE mapper PUBLIC "-//mybatis.org//DTD Mapper 3.0//EN" "http://mybatis.org/dtd/mybatis-3-mapper.dtd" >
<mapper namespace="com.lkcb.friendanswer.common.dao.StarBeanMapper" >
  <resultMap id="BaseResultMap" type="com.lkcb.friendanswer.common.bean.StarBean" >
    <!--
      WARNING - @mbggenerated
      This element is automatically generated by MyBatis Generator, do not modify.
    -->
    <id column="star_id" property="starId" jdbcType="BIGINT" />
    <result column="user_id" property="userId" jdbcType="INTEGER" />
    <result column="post_id" property="postId" jdbcType="BIGINT" />
    <result column="star_time" property="starTime" jdbcType="TIMESTAMP" />
  </resultMap>
  <sql id="Base_Column_List" >
    <!--
      WARNING - @mbggenerated
      This element is automatically generated by MyBatis Generator, do not modify.
    -->
    star_id, user_id, post_id, star_time
  </sql>
  <select id="selectByPrimaryKey" resultMap="BaseResultMap" parameterType="java.lang.Long" >
    <!--
      WARNING - @mbggenerated
      This element is automatically generated by MyBatis Generator, do not modify.
    -->
    select 
    <include refid="Base_Column_List" />
    from fa_star
    where star_id = #{starId,jdbcType=BIGINT}
  </select>
  <delete id="deleteByPrimaryKey" parameterType="java.lang.Long" >
    <!--
      WARNING - @mbggenerated
      This element is automatically generated by MyBatis Generator, do not modify.
    -->
    delete from fa_star
    where star_id = #{starId,jdbcType=BIGINT}
  </delete>
  <insert id="insert" parameterType="com.lkcb.friendanswer.common.bean.StarBean" >
    <!--
      WARNING - @mbggenerated
      This element is automatically generated by MyBatis Generator, do not modify.
    -->
    insert into fa_star (star_id, user_id, post_id, 
      star_time)
    values (#{starId,jdbcType=BIGINT}, #{userId,jdbcType=INTEGER}, #{postId,jdbcType=BIGINT}, 
      #{starTime,jdbcType=TIMESTAMP})
  </insert>
  <insert id="insertSelective" parameterType="com.lkcb.friendanswer.common.bean.StarBean" >
    <!--
      WARNING - @mbggenerated
      This element is automatically generated by MyBatis Generator, do not modify.
    -->
    insert into fa_star
    <trim prefix="(" suffix=")" suffixOverrides="," >
      <if test="starId != null" >
        star_id,
      </if>
      <if test="userId != null" >
        user_id,
      </if>
      <if test="postId != null" >
        post_id,
      </if>
      <if test="starTime != null" >
        star_time,
      </if>
    </trim>
    <trim prefix="values (" suffix=")" suffixOverrides="," >
      <if test="starId != null" >
        #{starId,jdbcType=BIGINT},
      </if>
      <if test="userId != null" >
        #{userId,jdbcType=INTEGER},
      </if>
      <if test="postId != null" >
        #{postId,jdbcType=BIGINT},
      </if>
      <if test="starTime != null" >
        #{starTime,jdbcType=TIMESTAMP},
      </if>
    </trim>
  </insert>
  <update id="updateByPrimaryKeySelective" parameterType="com.lkcb.friendanswer.common.bean.StarBean" >
    <!--
      WARNING - @mbggenerated
      This element is automatically generated by MyBatis Generator, do not modify.
    -->
    update fa_star
    <set >
      <if test="userId != null" >
        user_id = #{userId,jdbcType=INTEGER},
      </if>
      <if test="postId != null" >
        post_id = #{postId,jdbcType=BIGINT},
      </if>
      <if test="starTime != null" >
        star_time = #{starTime,jdbcType=TIMESTAMP},
      </if>
    </set>
    where star_id = #{starId,jdbcType=BIGINT}
  </update>
  <update id="updateByPrimaryKey" parameterType="com.lkcb.friendanswer.common.bean.StarBean" >
    <!--
      WARNING - @mbggenerated
      This element is automatically generated by MyBatis Generator, do not modify.
    -->
    update fa_star
    set user_id = #{userId,jdbcType=INTEGER},
      post_id = #{postId,jdbcType=BIGINT},
      star_time = #{starTime,jdbcType=TIMESTAMP}
    where star_id = #{starId,jdbcType=BIGINT}
  </update>
</mapper>